{"en": 0, "fr": 1, "zh": 2, "it": 3, "fa": 4, "nl": 5, "de": 6, "cn": 7, "ar": 8, "es": 9, "pl": 10, "hr": 11, "ru": 12, "mk": 13, "ja": 14, "sv": 15, "ko": 16, "sr": 17, "bn": 18, "he": 19, "pt": 20, "wo": 21, "hu": 22, "tl": 23, "cy": 24, "vi": 25, "cs": 26, "da": 27, "no": 28, "ka": 29, "nb": 30, "uk": 31, "xx": 32, "hi": 33, "tr": 34, "el": 35, "sh": 36, "ta": 37, "bo": 38, "ca": 39, "fi": 40, "th": 41, "sk": 42, "bs": 43, "iu": 44, "is": 45, "sl": 46, "ps": 47, "eo": 48, "se": 49, "ro": 50, "mn": 51, "bm": 52, "dz": 53, "hy": 54, "zu": 55, "af": 56, "la": 57, "et": 58, "lt": 59, "ku": 60, "fy": 61, "ur": 62, "rw": 63, "id": 64, "bg": 65, "mr": 66, "eu": 67, "kk": 68, "ms": 69, "ml": 70, "qu": 71, "uz": 72, "te": 73, "am": 74, "sq": 75, "jv": 76, "lv": 77, "tg": 78, "ln": 79, "lo": 80, "ff": 81, "ay": 82, "kn": 83, "ne": 84, "pa": 85, "ky": 86, "gu": 87, "gl": 88, "mi": 89, "sm": 90, "mt": 91, "ik": 92, "mo": 93}